poh/__init__.py
poh/__main__.py
poh/poh.py
poh-0.1.8.dist-info/DESCRIPTION.rst
poh-0.1.8.dist-info/METADATA
poh-0.1.8.dist-info/RECORD
poh-0.1.8.dist-info/WHEEL
poh-0.1.8.dist-info/entry_points.txt
poh-0.1.8.dist-info/metadata.json
poh-0.1.8.dist-info/top_level.txt
