Metadata-Version: 2.0
Name: poh
Version: 0.1.8
Summary: ssh commands runner
Home-page: https://github.com/slashfoo/poh
Author: Jamiel Almeida
Author-email: jamiel.almeida@gmail.com
License: MIT
Keywords: ssh admin remote command execution
Platform: UNKNOWN
Classifier: Development Status :: 3 - Alpha
Classifier: Programming Language :: Python :: 2
Classifier: Programming Language :: Python :: 2.7
Classifier: Programming Language :: Python :: 3
Classifier: Programming Language :: Python :: 3.5
